tipytools/__init__.py
tipytools/logger.py
tipytools/templates.py
tipytools/tipytools.py
tipytools/__pycache__/Log.cpython-311.pyc
tipytools/__pycache__/Logger.cpython-311.pyc
tipytools/__pycache__/__init__.cpython-311.pyc
tipytools/__pycache__/codium_00c022e0-7655-414b-a622-098beca9010a_logger.cpython-311-pytest-7.4.0.pyc
tipytools/__pycache__/codium_05000b82-e7e9-4001-a2ec-29837d04461d_logger.cpython-311-pytest-7.4.0.pyc
tipytools/__pycache__/codium_0c863777-eec2-41a4-b0ff-b09d0914bc71_logger.cpython-311-pytest-7.4.0.pyc
tipytools/__pycache__/codium_0d10180d-70b1-46ec-b0b2-00928de153ca_tipytools.cpython-311-pytest-7.4.0.pyc
tipytools/__pycache__/codium_1eae99a2-be22-4c24-a9c2-3f1c84306f6e_tipytools.cpython-311-pytest-7.4.0.pyc
tipytools/__pycache__/codium_27948659-617f-446f-9600-279dd232706a_logger.cpython-311-pytest-7.4.0.pyc
tipytools/__pycache__/codium_2823b1bf-548f-4f59-bbf4-b98defb3f460_tipytools.cpython-311-pytest-7.4.0.pyc
tipytools/__pycache__/codium_2ad1c9a9-1a8d-496b-9b92-877c8b83aced_logger.cpython-311-pytest-7.4.0.pyc
tipytools/__pycache__/codium_3969d507-2be5-49aa-a57b-9eadffbe41ea_tipytools.cpython-311-pytest-7.4.0.pyc
tipytools/__pycache__/codium_3bd8d02c-b579-4eb4-b056-a65c536deb0a_logger.cpython-311-pytest-7.4.0.pyc
tipytools/__pycache__/codium_569c7fac-d6b7-4130-97de-62751c6f0148_logger.cpython-311-pytest-7.4.0.pyc
tipytools/__pycache__/codium_5705d3ae-ac66-4c28-93c3-943e1cc851f6_logger.cpython-311-pytest-7.4.0.pyc
tipytools/__pycache__/codium_598e0022-ca24-4aed-809a-6d56b4beb4e6_logger.cpython-311-pytest-7.4.0.pyc
tipytools/__pycache__/codium_7018c4c7-c890-4a9d-a98e-6aa2eb9449e2_tipytools.cpython-311-pytest-7.4.0.pyc
tipytools/__pycache__/codium_77149a49-91dc-4367-9921-4f0fc90a14f8_logger.cpython-311-pytest-7.4.0.pyc
tipytools/__pycache__/codium_80bf8d7e-63ee-4c06-aed9-c042212341b8_logger.cpython-311-pytest-7.4.0.pyc
tipytools/__pycache__/codium_89d0dbf5-47b8-416d-abdc-5d770bf6dc6b_tipytools.cpython-311-pytest-7.4.0.pyc
tipytool-1.0.3.dist-info/METADATA
tipytool-1.0.3.dist-info/WHEEL
tipytool-1.0.3.dist-info/entry_points.txt
tipytool-1.0.3.dist-info/top_level.txt
tipytool-1.0.3.dist-info/RECORD
