Metadata-Version: 2.1
Name: tipytool
Version: 1.0.3
Summary: A tool for generating boilerplate for creating command-line tools
Author-email: Mauly dotDev <mauly.dev@gmail.com>
License: BSD-3-Clause
Keywords: command-line interface,development tools,Python library,CLI utilities,project scaffolding,automation,code generation,tooling,software development,command-line applications
Classifier: Programming Language :: Python :: 3
Classifier: Operating System :: OS Independent
Requires-Python: >=3.7
Requires-Dist: fire
